aspose/diagram/py.typed
aspose/pycore/py.typed
aspose/pycore/__init__.pyi
aspose/pyreflection/py.typed
aspose/pyreflection/__init__.pyi
aspose/pydrawing/py.typed
aspose/pydrawing/__init__.pyi
aspose/pydrawing/design.pyi
aspose/pydrawing/drawing2d.pyi
aspose/pydrawing/imaging.pyi
aspose/pydrawing/printing.pyi
aspose/pydrawing/text.pyi
aspose/diagram/__init__.pyi
aspose/diagram/activexcontrols/__init__.pyi
aspose/diagram/autolayout/__init__.pyi
aspose/diagram/lowcode/__init__.pyi
aspose/diagram/manipulation/__init__.pyi
aspose/diagram/printing/__init__.pyi
aspose/diagram/properties/__init__.pyi
aspose/diagram/saving/__init__.pyi
aspose/diagram/vba/__init__.pyi
.__pyi_patched
aspose/__init__.py
aspose/diagram.cpython-310-darwin.so
aspose/diagram.cpython-311-darwin.so
aspose/diagram.cpython-312-darwin.so
aspose/diagram.cpython-313-darwin.so
aspose/diagram.cpython-36m-darwin.so
aspose/diagram.cpython-37m-darwin.so
aspose/diagram.cpython-38-darwin.so
aspose/diagram.cpython-39-darwin.so
aspose/pycore.cpython-310-darwin.so
aspose/pycore.cpython-311-darwin.so
aspose/pycore.cpython-312-darwin.so
aspose/pycore.cpython-313-darwin.so
aspose/pycore.cpython-36m-darwin.so
aspose/pycore.cpython-37m-darwin.so
aspose/pycore.cpython-38-darwin.so
aspose/pycore.cpython-39-darwin.so
aspose/pygc.cpython-310-darwin.so
aspose/pygc.cpython-311-darwin.so
aspose/pygc.cpython-312-darwin.so
aspose/pygc.cpython-313-darwin.so
aspose/pygc.cpython-36m-darwin.so
aspose/pygc.cpython-37m-darwin.so
aspose/pygc.cpython-38-darwin.so
aspose/pygc.cpython-39-darwin.so
aspose/pyreflection.cpython-310-darwin.so
aspose/pyreflection.cpython-311-darwin.so
aspose/pyreflection.cpython-312-darwin.so
aspose/pyreflection.cpython-313-darwin.so
aspose/pyreflection.cpython-36m-darwin.so
aspose/pyreflection.cpython-37m-darwin.so
aspose/pyreflection.cpython-38-darwin.so
aspose/pyreflection.cpython-39-darwin.so
aspose/__pyinstaller/__init__.pyi
aspose/__pyinstaller/hook-aspose.py
aspose/assemblies/diagram/Aspose.Diagram.dll
aspose_diagram_python-25.12.0.dist-info/METADATA
aspose_diagram_python-25.12.0.dist-info/WHEEL
aspose_diagram_python-25.12.0.dist-info/entry_points.txt
aspose_diagram_python-25.12.0.dist-info/top_level.txt
aspose_diagram_python-25.12.0.dist-info/RECORD