Metadata-Version: 2.1
Name: aspose-diagram-python
Version: 25.12.0
Summary: Aspose.Diagram for Python via .NET  is a scalable and feature-rich API to process visio files using Python. API offers Visio file creation, manipulation, conversion and rendering. Developers can format pages to the most granular level, create and manipulate shape, render pages, shapes to PDF and images, and much more - all without any dependency on Microsoft Office or Visio application.
Home-page: https://products.aspose.com/diagram/
Author: aspose-diagram
License: https://company.aspose.com/legal/eula
Keywords: Excel,XLS,XLSX,XLSB,CSV,PDF,JPG,PNG,HTML,ODS,Numbers,XLSM,OOXML,Spreadsheet,Markdown,XPS,DOCX,PPTX,MHTML,TXT,JSON,SVG,EMF,TIFF
Platform: macos_x86_64
Classifier: Intended Audience :: Developers
Classifier: Intended Audience :: Education
Classifier: Intended Audience :: Manufacturing
Classifier: Intended Audience :: Science/Research
Classifier: Operating System :: Microsoft :: Windows
Classifier: Operating System :: POSIX :: Linux
Classifier: Operating System :: MacOS
Classifier: License :: Free To Use But Restricted
Classifier: License :: Other/Proprietary License
Classifier: Programming Language :: Python :: 3.6
Classifier: Programming Language :: Python :: 3.7
Classifier: Programming Language :: Python :: 3.8
Classifier: Programming Language :: Python :: 3.9
Classifier: Programming Language :: Python :: 3.10
Classifier: Programming Language :: Python :: 3.11
Classifier: Programming Language :: Python :: 3.12
Classifier: Programming Language :: Python :: 3.13
Classifier: Topic :: Software Development :: Libraries
Requires-Python: >=3.6,<3.14
